pytket/extensions/qiskit/__init__.py
pytket/extensions/qiskit/_metadata.py
pytket/extensions/qiskit/py.typed
pytket/extensions/qiskit/qiskit_convert.py
pytket/extensions/qiskit/result_convert.py
pytket/extensions/qiskit/tket_backend.py
pytket/extensions/qiskit/tket_job.py
pytket/extensions/qiskit/tket_pass.py
pytket/extensions/qiskit/backends/__init__.py
pytket/extensions/qiskit/backends/aer.py
pytket/extensions/qiskit/backends/config.py
pytket/extensions/qiskit/backends/crosstalk_model.py
pytket/extensions/qiskit/backends/ibm.py
pytket/extensions/qiskit/backends/ibm_utils.py
pytket/extensions/qiskit/backends/ibmq_emulator.py
pytket_qiskit-0.76.0.dist-info/licenses/LICENSE
tests/__init__.py
tests/backend_test.py
tests/conftest.py
tests/mock_pytket_backend.py
tests/qiskit_backend_test.py
tests/qiskit_convert_test.py
pytket_qiskit-0.76.0.dist-info/METADATA
pytket_qiskit-0.76.0.dist-info/WHEEL
pytket_qiskit-0.76.0.dist-info/top_level.txt
pytket_qiskit-0.76.0.dist-info/RECORD
