Metadata-Version: 2.4
Name: pytket-qiskit
Version: 0.76.0
Summary: Extension for pytket, providing translation to and from the Qiskit.
Author-email: TKET development team <tket-support@quantinuum.com>
Maintainer-email: TKET development team <tket-support@quantinuum.com>
License:                                  Apache License
Project-URL: documentation, https://tket.quantinuum.com/extensions/pytket-qiskit/index.html
Project-URL: source, https://github.com/Quantinuum/pytket-qiskit
Project-URL: tracker, https://github.com/Quantinuum/pytket-qiskit/issues
Classifier: Environment :: Console
Classifier: Programming Language :: Python :: 3.10
Classifier: Programming Language :: Python :: 3.11
Classifier: Programming Language :: Python :: 3.12
Classifier: Programming Language :: Python :: 3.13
Classifier: Operating System :: MacOS :: MacOS X
Classifier: Operating System :: POSIX :: Linux
Classifier: Operating System :: Microsoft :: Windows
Classifier: Intended Audience :: Developers
Classifier: Intended Audience :: Science/Research
Classifier: Topic :: Scientific/Engineering
Requires-Python: <4.0,>=3.10
License-File: LICENSE
Requires-Dist: pytket>=2.11.0
Requires-Dist: qiskit>=2.2.3
Requires-Dist: qiskit-ibm-runtime>=0.43.1
Requires-Dist: qiskit-aer>=0.17.1
Requires-Dist: numpy>=1.26.4
Requires-Dist: symengine>=0.11
Dynamic: license-file
